data_view/__init__.py
data_view-0.1.1.dist-info/METADATA
data_view-0.1.1.dist-info/WHEEL
data_view-0.1.1.dist-info/top_level.txt
data_view-0.1.1.dist-info/RECORD
