Metadata-Version: 2.1
Name: data-view
Version: 0.1.1
Summary: Automated view of dataset
Home-page: UNKNOWN
Author: Urev Oleg
Author-email: urevolegg@gmail.com
License: UNKNOWN
Platform: UNKNOWN
Classifier: Programming Language :: Python :: 3.6
Classifier: License :: OSI Approved :: MIT License
Classifier: Operating System :: OS Independent
Requires-Dist: pandas
Requires-Dist: numpy
Requires-Dist: matplotlib
Requires-Dist: ipython
Requires-Dist: seaborn
